REDi/LICENSE.txt
REDi/README.md
REDi/building.py
REDi/data/components_library.json
REDi/examples/example_building.json
REDi/go_redi.py
REDi/images/Arup.png
REDi/impeding_delays.py
REDi/main.py
REDi/process_component_lib.py
REDi/repair_schedules/get_repair_schedule.py
REDi/repair_schedules/scheduling_optimization/get_optimized_repair_schedule.py
REDi/repair_schedules/scheduling_optimization/synchronous_alloc.py
REDi/requirements.in
REDi/requirements.txt
REDi/test/__init__.py
REDi/test/conftest.py
REDi/test/fixtures/__init__.py
REDi/test/fixtures/assets.py
REDi/test/fixtures/mock_responses.py
REDi/test/test_REDi.py
REDi/utils/file_utils.py
REDi/utils/stat_utils.py
pyredi-0.1.1.dist-info/METADATA
pyredi-0.1.1.dist-info/WHEEL
pyredi-0.1.1.dist-info/RECORD
