Metadata-Version: 2.1
Name: pyredi
Version: 0.1.1
Summary: Python package for REDi - Resilient Design for the Next Generation of Buildings
License: Apache 2.0 - See LICENSE.txt
Author: Stevan.Gavrilovic
Author-email: stevan.gavrilovic@arup.com
Requires-Python: >=3.9,<3.13
Classifier: License :: Other/Proprietary License
Classifier: Programming Language :: Python :: 3
Classifier: Programming Language :: Python :: 3.9
Classifier: Programming Language :: Python :: 3.10
Classifier: Programming Language :: Python :: 3.11
Requires-Dist: numpy (>=1.25.2,<2.0.0)
Requires-Dist: pytest (>=7.4.0,<8.0.0)
Requires-Dist: scipy (>=1.11.2,<2.0.0)
Requires-Dist: simplejson (>=3.19.1,<4.0.0)
